{
  "timestamp": "2025-11-18T22:52:56.672864Z",
  "hmi": NaN,
  "hmi_band": "It's the future of finance",
  "weights": [
    {
      "asset": "BTC",
      "weight": 0.2982
    },
    {
      "asset": "ETH",
      "weight": 0.0
    },
    {
      "asset": "BNB",
      "weight": 0.085
    },
    {
      "asset": "SOL",
      "weight": 0.0873
    },
    {
      "asset": "DOGE",
      "weight": 0.1096
    },
    {
      "asset": "TON",
      "weight": 0.1384
    },
    {
      "asset": "SUI",
      "weight": 0.0673
    },
    {
      "asset": "UNI",
      "weight": 0.0714
    },
    {
      "asset": "STABLES",
      "weight": 0.1429
    }
  ]
}