{
  "timestamp": "2025-12-08T17:15:08.081454Z",
  "health": {
    "hmi_ok": true,
    "binance_ok": true,
    "supplies_ok": true,
    "bands_ok": true,
    "prices_ok": true,
    "json_written": false
  },
  "rows": [
    {
      "token": "BTC",
      "price": 90143.06,
      "mc": 1799123868732.4,
      "change_24h": 0.289,
      "btc_dom": null,
      "range": ""
    },
    {
      "token": "ETH",
      "price": 3116.16,
      "mc": 376106220148.1097,
      "change_24h": 2.489,
      "btc_dom": 82.7,
      "range": "73\u201390%"
    },
    {
      "token": "BNB",
      "price": 896.03,
      "mc": 123415549398.3848,
      "change_24h": 0.324,
      "btc_dom": 93.6,
      "range": "93\u201396%"
    },
    {
      "token": "SOL",
      "price": 136.06,
      "mc": 76196162796.57674,
      "change_24h": 3.084,
      "btc_dom": 95.9,
      "range": "92\u201396%"
    },
    {
      "token": "DOGE",
      "price": 0.14324,
      "mc": 23144355771.26846,
      "change_24h": 2.888,
      "btc_dom": 98.7,
      "range": "96\u201399%"
    },
    {
      "token": "TON",
      "price": 1.635,
      "mc": 3999128677.019068,
      "change_24h": 2.895,
      "btc_dom": 99.8,
      "range": "99\u2013100%"
    },
    {
      "token": "USDTC",
      "price": 1.0,
      "mc": 263772905597.55286,
      "change_24h": 0.0,
      "btc_dom": null,
      "range": ""
    },
    {
      "token": "SUI",
      "price": 1.6104,
      "mc": 6017849587.192547,
      "change_24h": 2.332,
      "btc_dom": 99.7,
      "range": "99\u2013100%"
    },
    {
      "token": "UNI",
      "price": 5.617,
      "mc": 3538178485.8219843,
      "change_24h": 2.053,
      "btc_dom": 99.8,
      "range": "99\u2013100%"
    }
  ]
}