{
  "timestamp": "2025-12-21T00:00:05.671692Z",
  "source": "coingecko",
  "supplies": {
    "BTC": {
      "id": "bitcoin",
      "circulating_supply": 19964878.0
    },
    "ETH": {
      "id": "ethereum",
      "circulating_supply": 120695016.1307867
    },
    "BNB": {
      "id": "binancecoin",
      "circulating_supply": 137735154.7
    },
    "SOL": {
      "id": "solana",
      "circulating_supply": 562294775.5582767
    },
    "DOGE": {
      "id": "dogecoin",
      "circulating_supply": 167960063126.5791
    },
    "TON": {
      "id": "the-open-network",
      "circulating_supply": 2451390379.960008
    },
    "SUI": {
      "id": "sui",
      "circulating_supply": 3736866360.651109
    },
    "UNI": {
      "id": "uniswap",
      "circulating_supply": 629905374.0113912
    },
    "USDT": {
      "id": "tether",
      "circulating_supply": 186824255260.0028
    },
    "USDC": {
      "id": "usd-coin",
      "circulating_supply": 77081190626.29057
    }
  },
  "missing": []
}